google/analytics/data/__init__.py
google/analytics/data/gapic_version.py
google/analytics/data/py.typed
google/analytics/data_v1alpha/__init__.py
google/analytics/data_v1alpha/gapic_metadata.json
google/analytics/data_v1alpha/gapic_version.py
google/analytics/data_v1alpha/py.typed
google/analytics/data_v1alpha/services/__init__.py
google/analytics/data_v1alpha/services/alpha_analytics_data/__init__.py
google/analytics/data_v1alpha/services/alpha_analytics_data/async_client.py
google/analytics/data_v1alpha/services/alpha_analytics_data/client.py
google/analytics/data_v1alpha/services/alpha_analytics_data/pagers.py
google/analytics/data_v1alpha/services/alpha_analytics_data/transports/__init__.py
google/analytics/data_v1alpha/services/alpha_analytics_data/transports/base.py
google/analytics/data_v1alpha/services/alpha_analytics_data/transports/grpc.py
google/analytics/data_v1alpha/services/alpha_analytics_data/transports/grpc_asyncio.py
google/analytics/data_v1alpha/services/alpha_analytics_data/transports/rest.py
google/analytics/data_v1alpha/services/alpha_analytics_data/transports/rest_base.py
google/analytics/data_v1alpha/types/__init__.py
google/analytics/data_v1alpha/types/analytics_data_api.py
google/analytics/data_v1alpha/types/data.py
google/analytics/data_v1beta/__init__.py
google/analytics/data_v1beta/gapic_metadata.json
google/analytics/data_v1beta/gapic_version.py
google/analytics/data_v1beta/py.typed
google/analytics/data_v1beta/services/__init__.py
google/analytics/data_v1beta/services/beta_analytics_data/__init__.py
google/analytics/data_v1beta/services/beta_analytics_data/async_client.py
google/analytics/data_v1beta/services/beta_analytics_data/client.py
google/analytics/data_v1beta/services/beta_analytics_data/pagers.py
google/analytics/data_v1beta/services/beta_analytics_data/transports/__init__.py
google/analytics/data_v1beta/services/beta_analytics_data/transports/base.py
google_analytics_data-0.18.18.dist-info/LICENSE
google_analytics_data-0.18.18.dist-info/METADATA
google_analytics_data-0.18.18.dist-info/WHEEL
google_analytics_data-0.18.18.dist-info/top_level.txt
google_analytics_data-0.18.18.dist-info/RECORD
